PROJ3/BPF.v
`timescale 1ns/1ps

module BPF
  (
   input CLK,
   input CAL_BPF,
   input PU_BPF,
   output RDY_BPF
   );

   reg 	  RDY_BPF=0;
   reg    AUX = 0;
   
   always@ (posedge CLK)
     begin
	if(CAL_BPF & PU_BPF)
	  begin
	     #10000
	     RDY_BPF<=1;
	  end
     end
   

   always@ (posedge CLK or negedge PU_BPF)
     begin
	if(PU_BPF == 0)
	  begin
	     RDY_BPF<=0;
	  end
     end
   


endmodule //BPF

PROJ3/SYNT.v
`timescale 1ns/1ps

module SYNT
  (
   input CLK,
   input CAL_SYNT,
   input PU_SYNT,
   output RDY_SYNT
   );

   reg    CAL_SYNT_STA=0;
   reg 	  RDY_SYNT=0;
   reg    AUX = 0;
   
   always@ (posedge CLK)
     begin
	if(CAL_SYNT & PU_SYNT)
	  begin
	     #14000
	     RDY_SYNT<=1;
	  end
     end
   

   always@ (posedge CLK or negedge PU_SYNT)
     begin
	if(PU_SYNT == 0)
	  begin
	     RDY_SYNT<=0;
	  end
     end   


endmodule //SYNT

PROJ3/IREF.v
`timescale 1ns/1ps

module IREF
  (
   input CLK,
   input CAL_IREF,
   input PU_IREF,
   output RDY_IREF
   );

   reg    CAL_IREF_STA=0;
   reg 	  RDY_IREF=0;
   reg    AUX = 0;
   
   always@ (posedge CLK)
     begin
	if(CAL_IREF & PU_IREF)
	  begin
	     #9000
	     RDY_IREF<=1;
	  end
     end
   

   always@(posedge CLK or negedge PU_IREF)
     begin
	if(PU_IREF == 0)
	  begin
	     RDY_IREF<=0;
	  end
     end
   


endmodule //IREF

PROJ3/CTRL.v
`timescale 1ns/1ps

module CTRL
  (
   input  CLK,
   input  PU_RX, 
   output RDY_RX
   );

   reg RDY_RX = 0;
   reg PU_IREF = 0;
   reg PU_BPF = 0;
   reg PU_SYNT = 0;
   reg CAL_SYNT = 0;
   reg CAL_IREF = 0;
   reg CAL_BPF = 0;
   
   wire RDY_IREF;
   wire RDY_BPF;
   wire RDY_SYNT;
   

   wire CAL_IREF_STA = 0;
   wire CAL_BPF_STA = 0;
   wire CAL_SYNT_STA = 0;

   reg TESTE;
   

   
   IREF iref(
	     .CLK(CLK),
	     .CAL_IREF(CAL_IREF),
	     .PU_IREF(PU_IREF),
	     .RDY_IREF(RDY_IREF)
	    );

   SYNT synt(
	     .CLK(CLK),
	     .CAL_SYNT(CAL_SYNT),
	     .PU_SYNT(PU_SYNT),
	     .RDY_SYNT(RDY_SYNT)
	    );

   BPF bpf(
	     .CLK(CLK),
	     .CAL_BPF(CAL_BPF),
	     .PU_BPF(PU_BPF),
	     .RDY_BPF(RDY_BPF)
	    );
  

  always@(posedge CLK)
    begin
       if(PU_RX==1)
	 begin
	    PU_IREF<=1;
	    PU_BPF<=1;
 	    PU_SYNT<=1;
	    CAL_IREF<=1;
	    CAL_SYNT<=1;
	    CAL_BPF<=1;
	 end
       if(RDY_IREF & RDY_SYNT & RDY_BPF)
	 begin
	    RDY_RX<=1;
	 end
    end


   always@ (posedge CLK or negedge PU_RX)
     begin
	if(PU_RX==0)
	  begin
	     RDY_RX<=0;
	     CAL_IREF<=0;
	     CAL_SYNT<=0;
	     CAL_BPF<=0;
	     PU_IREF<=0;
	     PU_BPF<=0;
	     PU_SYNT<=0;
	  end
     end
   
   
endmodule // CTRL

PROJ3/CTRL_tb.v
`timescale 1ns /1ps

module CTRL_tb;
   reg CLK=0;
   reg PU_RX=0;
   wire RDY_RX;

   CTRL ctr(
	    .CLK(CLK),
	    .PU_RX(PU_RX),
	    .RDY_RX(RDY_RX)
	    );
   


	initial begin 
		$dumpfile("top.vcd");
		$dumpvars();

	   #1000
	   
	   PU_RX=1;
	 
	   #19000

           PU_RX=0;

	   #10000

           PU_RX=1;

	   #20000	     
	     
       	   $finish;

	end

   always
      #100CLK=!CLK;
   
endmodule

PROJ3/top.vcd
$date
	Tue May 26 13:16:10 2020
$end
$version
	Icarus Verilog
$end
$timescale
	1ps
$end
$scope module CTRL_tb $end
$var wire 1 ! RDY_RX $end
$var reg 1 " CLK $end
$var reg 1 # PU_RX $end
$scope module ctr $end
$var wire 1 $ CAL_BPF_STA $end
$var wire 1 % CAL_IREF_STA $end
$var wire 1 & CAL_SYNT_STA $end
$var wire 1 " CLK $end
$var wire 1 # PU_RX $end
$var wire 1 ' RDY_SYNT $end
$var wire 1 ( RDY_IREF $end
$var wire 1 ) RDY_BPF $end
$var reg 1 * CAL_BPF $end
$var reg 1 + CAL_IREF $end
$var reg 1 , CAL_SYNT $end
$var reg 1 - PU_BPF $end
$var reg 1 . PU_IREF $end
$var reg 1 / PU_SYNT $end
$var reg 1 ! RDY_RX $end
$scope module bpf $end
$var wire 1 * CAL_BPF $end
$var wire 1 " CLK $end
$var wire 1 - PU_BPF $end
$var reg 1 0 AUX $end
$var reg 1 ) RDY_BPF $end
$upscope $end
$scope module iref $end
$var wire 1 + CAL_IREF $end
$var wire 1 " CLK $end
$var wire 1 . PU_IREF $end
$var reg 1 1 AUX $end
$var reg 1 2 CAL_IREF_STA $end
$var reg 1 ( RDY_IREF $end
$upscope $end
$scope module synt $end
$var wire 1 , CAL_SYNT $end
$var wire 1 " CLK $end
$var wire 1 / PU_SYNT $end
$var reg 1 3 AUX $end
$var reg 1 4 CAL_SYNT_STA $end
$var reg 1 ' RDY_SYNT $end
$upscope $end
$upscope $end
$upscope $end
$enddefinitions $end
#0
$dumpvars
04
03
02
01
00
0/
0.
0-
0,
0+
0*
0)
0(
0'
0&
0%
0$
0#
0"
0!
$end
#100000
1"
#200000
0"
#300000
1"
#400000
0"
#500000
1"
#600000
0"
#700000
1"
#800000
0"
#900000
1"
#1000000
0"
1#
#1100000
1*
1,
1+
1/
1-
1.
1"
#1200000
0"
#1300000
1"
#1400000
0"
#1500000
1"
#1600000
0"
#1700000
1"
#1800000
0"
#1900000
1"
#2000000
0"
#2100000
1"
#2200000
0"
#2300000
1"
#2400000
0"
#2500000
1"
#2600000
0"
#2700000
1"
#2800000
0"
#2900000
1"
#3000000
0"
#3100000
1"
#3200000
0"
#3300000
1"
#3400000
0"
#3500000
1"
#3600000
0"
#3700000
1"
#3800000
0"
#3900000
1"
#4000000
0"
#4100000
1"
#4200000
0"
#4300000
1"
#4400000
0"
#4500000
1"
#4600000
0"
#4700000
1"
#4800000
0"
#4900000
1"
#5000000
0"
#5100000
1"
#5200000
0"
#5300000
1"
#5400000
0"
#5500000
1"
#5600000
0"
#5700000
1"
#5800000
0"
#5900000
1"
#6000000
0"
#6100000
1"
#6200000
0"
#6300000
1"
#6400000
0"
#6500000
1"
#6600000
0"
#6700000
1"
#6800000
0"
#6900000
1"
#7000000
0"
#7100000
1"
#7200000
0"
#7300000
1"
#7400000
0"
#7500000
1"
#7600000
0"
#7700000
1"
#7800000
0"
#7900000
1"
#8000000
0"
#8100000
1"
#8200000
0"
#8300000
1"
#8400000
0"
#8500000
1"
#8600000
0"
#8700000
1"
#8800000
0"
#8900000
1"
#9000000
0"
#9100000
1"
#9200000
0"
#9300000
1"
#9400000
0"
#9500000
1"
#9600000
0"
#9700000
1"
#9800000
0"
#9900000
1"
#10000000
0"
#10100000
1"
#10200000
0"
#10300000
1(
1"
#10400000
0"
#10500000
1"
#10600000
0"
#10700000
1"
#10800000
0"
#10900000
1"
#11000000
0"
#11100000
1"
#11200000
0"
#11300000
1)
1"
#11400000
0"
#11500000
1"
#11600000
0"
#11700000
1"
#11800000
0"
#11900000
1"
#12000000
0"
#12100000
1"
#12200000
0"
#12300000
1"
#12400000
0"
#12500000
1"
#12600000
0"
#12700000
1"
#12800000
0"
#12900000
1"
#13000000
0"
#13100000
1"
#13200000
0"
#13300000
1"
#13400000
0"
#13500000
1"
#13600000
0"
#13700000
1"
#13800000
0"
#13900000
1"
#14000000
0"
#14100000
1"
#14200000
0"
#14300000
1"
#14400000
0"
#14500000
1"
#14600000
0"
#14700000
1"
#14800000
0"
#14900000
1"
#15000000
0"
#15100000
1"
#15200000
0"
#15300000
1'
1"
#15400000
0"
#15500000
1!
1"
#15600000
0"
#15700000
1"
#15800000
0"
#15900000
1"
#16000000
0"
#16100000
1"
#16200000
0"
#16300000
1"
#16400000
0"
#16500000
1"
#16600000
0"
#16700000
1"
#16800000
0"
#16900000
1"
#17000000
0"
#17100000
1"
#17200000
0"
#17300000
1"
#17400000
0"
#17500000
1"
#17600000
0"
#17700000
1"
#17800000
0"
#17900000
1"
#18000000
0"
#18100000
1"
#18200000
0"
#18300000
1"
#18400000
0"
#18500000
1"
#18600000
0"
#18700000
1"
#18800000
0"
#18900000
1"
#19000000
0"
#19100000
1"
#19200000
0"
#19300000
1"
#19400000
0"
#19500000
1"
#19600000
0"
#19700000
1"
#19800000
0"
#19900000
1"
#20000000
0'
0)
0(
0/
0-
0.
0*
0,
0+
0!
0"
0#
#20100000
1"
#20200000
0"
#20300000
1"
#20400000
0"
#20500000
1"
#20600000
0"
#20700000
1"
#20800000
0"
#20900000
1"
#21000000
0"
#21100000
1"
#21200000
0"
#21300000
0)
1"
