PROJ3/BPF.v
`timescale 1ns/1ps

module BPF
  (
   input CLK,
   input CAL_BPF,
   input PU_BPF,
   output RDY_BPF
   );

   reg 	  RDY_BPF=0;
   reg    AUX = 0;

   reg [32:0] counter = 0;
   
   
 always @(posedge CLK) begin
    if (!PU_BPF) begin
        counter <= 40;  /*Tcal + Trdy = 8us => 8 * 5 = 40 */
        RDY_BPF <= 0;
    end else if (counter > 0) begin
       if(CAL_BPF==1)begin
        counter <= counter - 1;
       end
    end else begin
        RDY_BPF <= 1;
    end
end

endmodule //BPF

PROJ3/SYNT.v
`timescale 1ns/1ps

module SYNT
  (
   input CLK,
   input CAL_SYNT,
   input PU_SYNT,
   output RDY_SYNT
   );

   reg    CAL_SYNT_STA=0;
   reg 	  RDY_SYNT=0;
   reg    AUX = 0;
   
   reg [32:0] counter = 0;

always @(posedge CLK) begin
    if (!PU_SYNT) begin
        counter <= 60;  /*Tcal + Trdy = 12us => 12 * 5 = 60*/
        RDY_SYNT <= 0;
    end else if (counter > 0) begin
       if(CAL_SYNT==1)begin
        counter <= counter - 1;
       end
    end else begin
        RDY_SYNT <= 1;
    end
end


endmodule //SYNT

PROJ3/IREF.v
`timescale 1ns/1ps

module IREF
  (
   input CLK,
   input CAL_IREF,
   input PU_IREF,
   output RDY_IREF
   );

   reg    CAL_IREF_STA=0;
   reg 	  RDY_IREF=0;
   reg    AUX = 0;

   reg [32:0] counter = 0;

always @(posedge CLK) begin
    if (!PU_IREF) begin
        counter <= 35;  /*Tcal + Trdy = 7us => 7 * 5 = 35*/
        RDY_IREF <= 0;
    end else if (counter > 0) begin
        if(CAL_IREF==1)begin
        counter <= counter - 1;
       end
    end else begin
        RDY_IREF <= 1;
    end
end
   
   
endmodule //IREF

PROJ3/CTRL.v
`timescale 1ns/1ps

module CTRL
  (
   input  CLK,
   input  PU_RX, 
   output RDY_RX
   );

   reg RDY_RX = 0;
   reg PU_IREF = 0;
   reg PU_BPF = 0;
   reg PU_SYNT = 0;
   reg CAL_SYNT = 0;
   reg CAL_IREF = 0;
   reg CAL_BPF = 0;
   
   wire RDY_IREF;
   wire RDY_BPF;
   wire RDY_SYNT;
   

   wire CAL_IREF_STA = 0;
   wire CAL_BPF_STA = 0;
   wire CAL_SYNT_STA = 0;

   reg TESTE;
   reg [32:0] counter = 0;

   
   IREF iref(
	     .CLK(CLK),
	     .CAL_IREF(CAL_IREF),
	     .PU_IREF(PU_IREF),
	     .RDY_IREF(RDY_IREF)
	    );

   SYNT synt(
	     .CLK(CLK),
	     .CAL_SYNT(CAL_SYNT),
	     .PU_SYNT(PU_SYNT),
	     .RDY_SYNT(RDY_SYNT)
	    );

   BPF bpf(
	     .CLK(CLK),
	     .CAL_BPF(CAL_BPF),
	     .PU_BPF(PU_BPF),
	     .RDY_BPF(RDY_BPF)
	    );
 
   always@ (posedge CLK or negedge PU_RX)
     begin
	if(PU_RX==0)
	  begin
	     counter<=10; /* 10 = 2us * 5 */
	     RDY_RX<=0;
	     CAL_IREF<=0;
	     CAL_SYNT<=0;
	     CAL_BPF<=0;
	     PU_IREF<=0;
	     PU_BPF<=0;
	     PU_SYNT<=0;
	  end
	else begin
	   PU_IREF<=1;
	   PU_BPF<=1;
	   PU_SYNT<=1;
	   if(counter > 0)begin
	      counter <= counter - 1;
	   end
	   else begin
	      CAL_IREF<=1;
	      CAL_BPF<=1;
	      CAL_SYNT<=1;
	   end
	end 

	if(RDY_IREF & RDY_SYNT & RDY_BPF)
	 begin
	    RDY_RX<=1;
	 end
     end
   
   
endmodule // CTRL

PROJ3/CTRL_tb.v
`timescale 1ns /1ps

module CTRL_tb;
   reg CLK=0;
   reg PU_RX=0;
   wire RDY_RX;

   CTRL ctr(
	    .CLK(CLK),
	    .PU_RX(PU_RX),
	    .RDY_RX(RDY_RX)
	    );
   


	initial begin 
		$dumpfile("top.vcd");
		$dumpvars();

	   #1000
	   
	   PU_RX=1;
	 
	   #25000

           PU_RX=0;

	   #10000

           PU_RX=1;

	   #20000	     
	     
       	   $finish;

	end

   always
      #100CLK=!CLK;
   
endmodule

PROJ3/top.vcd
$date
	Fri May 29 07:24:58 2020
$end
$version
	Icarus Verilog
$end
$timescale
	1ps
$end
$scope module CTRL_tb $end
$var wire 1 ! RDY_RX $end
$var reg 1 " CLK $end
$var reg 1 # PU_RX $end
$scope module ctr $end
$var wire 1 $ CAL_BPF_STA $end
$var wire 1 % CAL_IREF_STA $end
$var wire 1 & CAL_SYNT_STA $end
$var wire 1 " CLK $end
$var wire 1 # PU_RX $end
$var wire 1 ' RDY_SYNT $end
$var wire 1 ( RDY_IREF $end
$var wire 1 ) RDY_BPF $end
$var reg 1 * CAL_BPF $end
$var reg 1 + CAL_IREF $end
$var reg 1 , CAL_SYNT $end
$var reg 1 - PU_BPF $end
$var reg 1 . PU_IREF $end
$var reg 1 / PU_SYNT $end
$var reg 1 ! RDY_RX $end
$var reg 33 0 counter [32:0] $end
$scope module bpf $end
$var wire 1 * CAL_BPF $end
$var wire 1 " CLK $end
$var wire 1 - PU_BPF $end
$var reg 1 1 AUX $end
$var reg 1 ) RDY_BPF $end
$var reg 33 2 counter [32:0] $end
$upscope $end
$scope module iref $end
$var wire 1 + CAL_IREF $end
$var wire 1 " CLK $end
$var wire 1 . PU_IREF $end
$var reg 1 3 AUX $end
$var reg 1 4 CAL_IREF_STA $end
$var reg 1 ( RDY_IREF $end
$var reg 33 5 counter [32:0] $end
$upscope $end
$scope module synt $end
$var wire 1 , CAL_SYNT $end
$var wire 1 " CLK $end
$var wire 1 / PU_SYNT $end
$var reg 1 6 AUX $end
$var reg 1 7 CAL_SYNT_STA $end
$var reg 1 ' RDY_SYNT $end
$var reg 33 8 counter [32:0] $end
$upscope $end
$upscope $end
$upscope $end
$enddefinitions $end
#0
$dumpvars
b0 8
07
06
b0 5
04
03
b0 2
01
b1010 0
0/
0.
0-
0,
0+
0*
0)
0(
0'
0&
0%
0$
0#
0"
0!
$end
#100000
b100011 5
b111100 8
b101000 2
1"
#200000
0"
#300000
1"
#400000
0"
#500000
1"
#600000
0"
#700000
1"
#800000
0"
#900000
1"
#1000000
0"
1#
#1100000
b1001 0
1/
1-
1.
1"
#1200000
0"
#1300000
b1000 0
1"
#1400000
0"
#1500000
b111 0
1"
#1600000
0"
#1700000
b110 0
1"
#1800000
0"
#1900000
b101 0
1"
#2000000
0"
#2100000
b100 0
1"
#2200000
0"
#2300000
b11 0
1"
#2400000
0"
#2500000
b10 0
1"
#2600000
0"
#2700000
b1 0
1"
#2800000
0"
#2900000
b0 0
1"
#3000000
0"
#3100000
1,
1*
1+
1"
#3200000
0"
#3300000
b100010 5
b111011 8
b100111 2
1"
#3400000
0"
#3500000
b100110 2
b111010 8
b100001 5
1"
#3600000
0"
#3700000
b100000 5
b111001 8
b100101 2
1"
#3800000
0"
#3900000
b100100 2
b111000 8
b11111 5
1"
#4000000
0"
#4100000
b11110 5
b110111 8
b100011 2
1"
#4200000
0"
#4300000
b100010 2
b110110 8
b11101 5
1"
#4400000
0"
#4500000
b11100 5
b110101 8
b100001 2
1"
#4600000
0"
#4700000
b100000 2
b110100 8
b11011 5
1"
#4800000
0"
#4900000
b11010 5
b110011 8
b11111 2
1"
#5000000
0"
#5100000
b11110 2
b110010 8
b11001 5
1"
#5200000
0"
#5300000
b11000 5
b110001 8
b11101 2
1"
#5400000
0"
#5500000
b11100 2
b110000 8
b10111 5
1"
#5600000
0"
#5700000
b10110 5
b101111 8
b11011 2
1"
#5800000
0"
#5900000
b11010 2
b101110 8
b10101 5
1"
#6000000
0"
#6100000
b10100 5
b101101 8
b11001 2
1"
#6200000
0"
#6300000
b11000 2
b101100 8
b10011 5
1"
#6400000
0"
#6500000
b10010 5
b101011 8
b10111 2
1"
#6600000
0"
#6700000
b10110 2
b101010 8
b10001 5
1"
#6800000
0"
#6900000
b10000 5
b101001 8
b10101 2
1"
#7000000
0"
#7100000
b10100 2
b101000 8
b1111 5
1"
#7200000
0"
#7300000
b1110 5
b100111 8
b10011 2
1"
#7400000
0"
#7500000
b10010 2
b100110 8
b1101 5
1"
#7600000
0"
#7700000
b1100 5
b100101 8
b10001 2
1"
#7800000
0"
#7900000
b10000 2
b100100 8
b1011 5
1"
#8000000
0"
#8100000
b1010 5
b100011 8
b1111 2
1"
#8200000
0"
#8300000
b1110 2
b100010 8
b1001 5
1"
#8400000
0"
#8500000
b1000 5
b100001 8
b1101 2
1"
#8600000
0"
#8700000
b1100 2
b100000 8
b111 5
1"
#8800000
0"
#8900000
b110 5
b11111 8
b1011 2
1"
#9000000
0"
#9100000
b1010 2
b11110 8
b101 5
1"
#9200000
0"
#9300000
b100 5
b11101 8
b1001 2
1"
#9400000
0"
#9500000
b1000 2
b11100 8
b11 5
1"
#9600000
0"
#9700000
b10 5
b11011 8
b111 2
1"
#9800000
0"
#9900000
b110 2
b11010 8
b1 5
1"
#10000000
0"
#10100000
b0 5
b11001 8
b101 2
1"
#10200000
0"
#10300000
b100 2
b11000 8
1(
1"
#10400000
0"
#10500000
b10111 8
b11 2
1"
#10600000
0"
#10700000
b10 2
b10110 8
1"
#10800000
0"
#10900000
b10101 8
b1 2
1"
#11000000
0"
#11100000
b0 2
b10100 8
1"
#11200000
0"
#11300000
b10011 8
1)
1"
#11400000
0"
#11500000
b10010 8
1"
#11600000
0"
#11700000
b10001 8
1"
#11800000
0"
#11900000
b10000 8
1"
#12000000
0"
#12100000
b1111 8
1"
#12200000
0"
#12300000
b1110 8
1"
#12400000
0"
#12500000
b1101 8
1"
#12600000
0"
#12700000
b1100 8
1"
#12800000
0"
#12900000
b1011 8
1"
#13000000
0"
#13100000
b1010 8
1"
#13200000
0"
#13300000
b1001 8
1"
#13400000
0"
#13500000
b1000 8
1"
#13600000
0"
#13700000
b111 8
1"
#13800000
0"
#13900000
b110 8
1"
#14000000
0"
#14100000
b101 8
1"
#14200000
0"
#14300000
b100 8
1"
#14400000
0"
#14500000
b11 8
1"
#14600000
0"
#14700000
b10 8
1"
#14800000
0"
#14900000
b1 8
1"
#15000000
0"
#15100000
b0 8
1"
#15200000
0"
#15300000
1'
1"
#15400000
0"
#15500000
1!
1"
